odoo/addons/l10n_fi_payment_terms/README.rst
odoo/addons/l10n_fi_payment_terms/__init__.py
odoo/addons/l10n_fi_payment_terms/__manifest__.py
odoo/addons/l10n_fi_payment_terms/data/payment_terms_finnish.xml
odoo/addons/l10n_fi_payment_terms/i18n/fi.po
odoo/addons/l10n_fi_payment_terms/i18n/l10n_fi_payment_terms.pot
odoo/addons/l10n_fi_payment_terms/readme/CONFIGURE.md
odoo/addons/l10n_fi_payment_terms/readme/CONTRIBUTORS.md
odoo/addons/l10n_fi_payment_terms/readme/CREDITS.md
odoo/addons/l10n_fi_payment_terms/readme/DESCRIPTION.md
odoo/addons/l10n_fi_payment_terms/readme/HISTORY.md
odoo/addons/l10n_fi_payment_terms/readme/MAINTAINER.rst
odoo/addons/l10n_fi_payment_terms/static/description/icon.png
odoo/addons/l10n_fi_payment_terms/static/description/index.html
odoo_addon_l10n_fi_payment_terms-17.0.1.0.0.2.dist-info/METADATA
odoo_addon_l10n_fi_payment_terms-17.0.1.0.0.2.dist-info/WHEEL
odoo_addon_l10n_fi_payment_terms-17.0.1.0.0.2.dist-info/top_level.txt
odoo_addon_l10n_fi_payment_terms-17.0.1.0.0.2.dist-info/RECORD
