Metadata-Version: 2.1
Name: odoo-addon-l10n_fi_payment_terms
Version: 17.0.1.0.0.2
Requires-Python: >=3.10
Requires-Dist: odoo>=17.0a,<17.1dev
Summary: Common Finnish invoice payment terms
Home-page: https://github.com/OCA/l10n-finland
License: AGPL-3
Author: Futural, Odoo Community Association (OCA)
Author-email: support@odoo-community.org
Classifier: Programming Language :: Python
Classifier: Framework :: Odoo
Classifier: Framework :: Odoo :: 17.0
Classifier: License :: OSI Approved :: GNU Affero General Public License v3
